MANIFEST.in
README.rst
package.json
setup.cfg
setup.py
anyex/_1broker.py
anyex/_1btcxe.py
anyex/__init__.py
anyex/acx.py
anyex/allcoin.py
anyex/anxpro.py
anyex/bibox.py
anyex/binance.py
anyex/bit2c.py
anyex/bitbank.py
anyex/bitbay.py
anyex/bitfinex.py
anyex/bitfinex2.py
anyex/bitflyer.py
anyex/bithumb.py
anyex/bitkk.py
anyex/bitlish.py
anyex/bitmarket.py
anyex/bitmex.py
anyex/bitso.py
anyex/bitstamp.py
anyex/bitstamp1.py
anyex/bittrex.py
anyex/bitz.py
anyex/bl3p.py
anyex/bleutrade.py
anyex/braziliex.py
anyex/btcbox.py
anyex/btcchina.py
anyex/btcexchange.py
anyex/btcmarkets.py
anyex/btctradeim.py
anyex/btctradeua.py
anyex/btcturk.py
anyex/btcx.py
anyex/bxinth.py
anyex/ccex.py
anyex/cex.py
anyex/chbtc.py
anyex/chilebit.py
anyex/cobinhood.py
anyex/coincheck.py
anyex/coinegg.py
anyex/coinex.py
anyex/coinexchange.py
anyex/coinfloor.py
anyex/coingi.py
anyex/coinmarketcap.py
anyex/coinmate.py
anyex/coinnest.py
anyex/coinone.py
anyex/coinsecure.py
anyex/coinspot.py
anyex/coolcoin.py
anyex/cryptopia.py
anyex/dsx.py
anyex/ethfinex.py
anyex/exmo.py
anyex/exx.py
anyex/flowbtc.py
anyex/foxbit.py
anyex/fybse.py
anyex/fybsg.py
anyex/gatecoin.py
anyex/gateio.py
anyex/gdax.py
anyex/gemini.py
anyex/getbtc.py
anyex/hadax.py
anyex/hitbtc.py
anyex/hitbtc2.py
anyex/huobi.py
anyex/huobicny.py
anyex/huobipro.py
anyex/ice3x.py
anyex/independentreserve.py
anyex/indodax.py
anyex/itbit.py
anyex/jubi.py
anyex/kraken.py
anyex/kucoin.py
anyex/kuna.py
anyex/lakebtc.py
anyex/lbank.py
anyex/liqui.py
anyex/livecoin.py
anyex/luno.py
anyex/lykke.py
anyex/mercado.py
anyex/mixcoins.py
anyex/negociecoins.py
anyex/nova.py
anyex/okcoincny.py
anyex/okcoinusd.py
anyex/okex.py
anyex/paymium.py
anyex/poloniex.py
anyex/qryptos.py
anyex/quadrigacx.py
anyex/quoinex.py
anyex/southxchange.py
anyex/surbitcoin.py
anyex/therock.py
anyex/tidebit.py
anyex/tidex.py
anyex/urdubit.py
anyex/vaultoro.py
anyex/vbtc.py
anyex/virwox.py
anyex/wex.py
anyex/xbtce.py
anyex/yobit.py
anyex/yunbi.py
anyex/zaif.py
anyex/zb.py
anyex.egg-info/PKG-INFO
anyex.egg-info/SOURCES.txt
anyex.egg-info/dependency_links.txt
anyex.egg-info/requires.txt
anyex.egg-info/top_level.txt
